virtualitics_sdk/__init__.py
virtualitics_sdk/__init__.pyi
virtualitics_sdk/app/__init__.py
virtualitics_sdk/app/__init__.pyi
virtualitics_sdk/app/app.pyi
virtualitics_sdk/app/flow_metadata.pyi
virtualitics_sdk/app/step.pyi
virtualitics_sdk/assets/__init__.py
virtualitics_sdk/assets/__init__.pyi
virtualitics_sdk/assets/asset.pyi
virtualitics_sdk/assets/dataset.pyi
virtualitics_sdk/assets/model.pyi
virtualitics_sdk/assets/schema.pyi
virtualitics_sdk/elements/__init__.py
virtualitics_sdk/elements/__init__.pyi
virtualitics_sdk/elements/button.pyi
virtualitics_sdk/elements/custom_event.pyi
virtualitics_sdk/elements/dashboard.pyi
virtualitics_sdk/elements/data_source.pyi
virtualitics_sdk/elements/date_time_range.pyi
virtualitics_sdk/elements/dropdown.pyi
virtualitics_sdk/elements/dropdown_data_sources.pyi
virtualitics_sdk/elements/element.pyi
virtualitics_sdk/elements/image.pyi
virtualitics_sdk/elements/infograph.pyi
virtualitics_sdk/elements/numeric_range.pyi
virtualitics_sdk/elements/plotly_plot.pyi
virtualitics_sdk/elements/rich_text.pyi
virtualitics_sdk/elements/table.pyi
virtualitics_sdk/elements/text_input.pyi
virtualitics_sdk/elements/xai_dashboard.pyi
virtualitics_sdk/exceptions/__init__.py
virtualitics_sdk/exceptions/__init__.pyi
virtualitics_sdk/exceptions/exception.pyi
virtualitics_sdk/icons/__init__.py
virtualitics_sdk/icons/__init__.pyi
virtualitics_sdk/icons/fonts.pyi
virtualitics_sdk/llm/__init__.py
virtualitics_sdk/llm/__init__.pyi
virtualitics_sdk/llm/agent.pyi
virtualitics_sdk/llm/chat.pyi
virtualitics_sdk/llm/types.pyi
virtualitics_sdk/page/__init__.py
virtualitics_sdk/page/__init__.pyi
virtualitics_sdk/page/card.pyi
virtualitics_sdk/page/comment.pyi
virtualitics_sdk/page/drilldown.pyi
virtualitics_sdk/page/page.pyi
virtualitics_sdk/page/section.pyi
virtualitics_sdk/persistence_client/__init__.py
virtualitics_sdk/persistence_client/__init__.pyi
virtualitics_sdk/persistence_client/client.pyi
virtualitics_sdk/persistence_client/internal/__init__.py
virtualitics_sdk-1.49.0.dist-info/METADATA
virtualitics_sdk-1.49.0.dist-info/WHEEL
virtualitics_sdk-1.49.0.dist-info/RECORD
