Metadata-Version: 2.4
Name: virtualitics-sdk
Version: 1.49.0
Summary: Virtualitics SDK (stubs-only wheel)
Author: Virtualitics Engineering
Author-email: engineering@virtualitics.com
Requires-Python: >=3.11,<3.12
Classifier: Programming Language :: Python :: 3
Classifier: Programming Language :: Python :: 3.11
